{"version":"2.0","class":"dataset","label":"Frequency of being happy in the last 4 weeks by age, sex and educational attainment level","source":"ESTAT","updated":"2024-01-03T23:00:00+0100","value":{"38":14.1,"39":14.4,"0":14.8,"1":16.9,"2":5.5,"3":7.0,"24":9.2,"25":8.8,"4":6.7,"5":6.8,"8":5.9,"9":6.4,"6":15.5,"7":14.0,"10":5.9,"11":7.1,"14":6.4,"15":9.9,"16":19.1,"17":28.5,"50":11.2,"51":12.3,"18":12.4,"19":15.5,"20":4.7,"21":5.3,"32":8.3,"33":9.7,"12":13.6,"13":17.4,"22":11.3,"23":16.4,"28":9.9,"29":8.1,"30":13.6,"31":14.9,"26":5.4,"27":4.1,"34":15.0,"35":5.7,"36":21.0,"37":15.3,"40":13.2,"41":16.6,"42":16.6,"43":15.3,"44":5.7,"45":4.7,"52":15.1,"53":12.8,"46":11.7,"47":10.1,"48":7.8,"49":9.6,"54":13.2,"55":12.7,"94":57.2,"95":61.5,"56":57.8,"57":59.2,"58":29.1,"59":27.9,"80":40.6,"81":45.9,"60":38.6,"61":44.8,"64":56.1,"65":58.1,"62":60.2,"63":55.7,"66":38.7,"67":44.3,"70":25.2,"71":36.5,"72":44.1,"73":43.0,"106":66.1,"107":63.6,"74":49.9,"75":52.2,"76":33.2,"77":36.5,"88":47.3,"89":48.1,"68":61.6,"69":63.3,"78":33.4,"79":32.7,"84":38.1,"85":37.3,"86":61.6,"87":59.0,"82":25.9,"83":26.6,"90":52.5,"91":56.1,"92":61.2,"93":60.9,"96":54.4,"97":51.9,"98":34.8,"99":40.7,"100":33.4,"101":41.7,"108":52.4,"109":51.8,"102":53.7,"103":48.8,"104":51.2,"105":48.2,"110":55.4,"111":57.5},"status":{"5":"u","19":"u","21":"u","13":"u","29":"u","27":"u","41":"u","55":"u","61":"u","75":"u","77":"u","69":"u","85":"u","83":"u","97":"u","111":"u"},"id":["freq","unit","isced11","frequenc","sex","age","geo","time"],"size":[1,1,1,2,1,1,28,2],"dimension":{"freq":{"label":"Time frequency","category":{"index":{"A":0},"label":{"A":"Annual"}}},"unit":{"label":"Unit of measure","category":{"index":{"PC":0},"label":{"PC":"Percentage"}}},"isced11":{"label":"International Standard Classification of Education (ISCED 2011)","category":{"index":{"TOTAL":0},"label":{"TOTAL":"All ISCED 2011 levels"}}},"frequenc":{"label":"Frequency","category":{"index":{"ALW":0,"MOST":1},"label":{"ALW":"Always","MOST":"Most of the time"}}},"sex":{"label":"Sex","category":{"index":{"T":0},"label":{"T":"Total"}}},"age":{"label":"Age class","category":{"index":{"Y_GE16":0},"label":{"Y_GE16":"16 years or over"}}},"geo":{"label":"Geopolitical entity (reporting)","category":{"index":{"BE":0,"BG":1,"CZ":2,"DK":3,"DE":4,"EE":5,"IE":6,"EL":7,"ES":8,"FR":9,"HR":10,"IT":11,"CY":12,"LV":13,"LT":14,"LU":15,"HU":16,"MT":17,"NL":18,"AT":19,"PL":20,"PT":21,"RO":22,"SI":23,"SK":24,"FI":25,"SE":26,"UK":27},"label":{"BE":"Belgium","BG":"Bulgaria","CZ":"Czechia","DK":"Denmark","DE":"Germany","EE":"Estonia","IE":"Ireland","EL":"Greece","ES":"Spain","FR":"France","HR":"Croatia","IT":"Italy","CY":"Cyprus","LV":"Latvia","LT":"Lithuania","LU":"Luxembourg","HU":"Hungary","MT":"Malta","NL":"Netherlands","AT":"Austria","PL":"Poland","PT":"Portugal","RO":"Romania","SI":"Slovenia","SK":"Slovakia","FI":"Finland","SE":"Sweden","UK":"United Kingdom"}}},"time":{"label":"Time","category":{"index":{"2013":0,"2018":1},"label":{"2013":"2013","2018":"2018"}}}},"extension":{"lang":"EN","id":"ILC_PW08","agencyId":"ESTAT","version":"1.0","datastructure":{"id":"ILC_PW08","agencyId":"ESTAT","version":"26.0"},"annotation":[{"type":"DISSEMINATION_DOI_XML","title":"<adms:identifier xmlns:adms=\"http://www.w3.org/ns/adms#\" xmlns:skos=\"http://www.w3.org/2004/02/skos/core.html\" xmlns:dct=\"http://purl.org/dc/terms/\" xmlns:rdf=\"http://www.w3.org/1999/02/22-rdf-syntax-ns#\"><adms:Identifier rdf:about=\"https://doi.org/10.2908/ILC_PW08\"><skos:notation rdf:datatype=\"http://purl.org/spar/datacite/doi\">10.2908/ILC_PW08</skos:notation><dct:creator rdf:resource=\"http://publications.europa.eu/resource/authority/corporate-body/ESTAT\"/><dct:issued rdf:datatype=\"http://www.w3.org/2001/XMLSchema#date\">2023-01-19</dct:issued></adms:Identifier></adms:identifier>"},{"type":"DISSEMINATION_OBJECT_TYPE","title":"DATASET"},{"type":"ESMS_HTML","title":"Explanatory texts (metadata)","href":"https://ec.europa.eu/eurostat/cache/metadata/en/ilc_sieusilc.htm"},{"type":"ESMS_SDMX","title":"Explanatory texts (metadata)","href":"https://ec.europa.eu/eurostat/api/dissemination/files?file=metadata/ilc_sieusilc.sdmx.zip"},{"type":"OBS_COUNT","title":"39627"},{"type":"OBS_PERIOD_OVERALL_LATEST","title":"2018"},{"type":"OBS_PERIOD_OVERALL_OLDEST","title":"2013"},{"type":"SOURCE_INSTITUTIONS","text":"Eurostat"},{"type":"UPDATE_DATA","date":"2023-06-27T23:00:00+0200"},{"type":"UPDATE_STRUCTURE","date":"2024-01-03T23:00:00+0100"}],"status":{"label":{"u":"low reliability"}},"positions-with-no-data":{"freq":[],"unit":[],"isced11":[],"frequenc":[],"sex":[],"age":[],"geo":[],"time":[]}}}