{"version":"2.0","class":"dataset","label":"Ratio of pupils and students to teachers and academic staff by education level and programme orientation","source":"ESTAT","updated":"2023-07-06T23:00:00+0200","value":{"171":10.1,"172":10.1,"173":10.1,"174":10.0,"175":9.8,"176":9.9,"177":10.0,"178":10.1,"179":10.1,"0":10.8,"1":10.8,"3":10.7,"4":10.7,"5":10.6,"6":10.6,"7":10.4,"8":9.3,"9":13.9,"10":14.0,"11":14.0,"12":13.9,"13":13.3,"14":12.8,"15":12.1,"16":11.4,"17":11.1,"108":11.3,"109":11.4,"110":11.1,"111":10.7,"112":10.7,"113":10.6,"114":10.4,"115":10.4,"116":10.1,"18":13.2,"19":13.8,"20":13.7,"21":13.8,"22":13.9,"23":14.2,"24":13.8,"25":13.5,"26":13.2,"36":14.1,"37":13.9,"38":13.8,"39":13.7,"40":13.7,"41":13.6,"42":13.4,"43":13.3,"44":13.2,"28":12.0,"29":12.0,"30":11.6,"31":11.5,"32":11.5,"33":11.5,"34":11.9,"35":11.8,"45":12.4,"46":12.5,"47":12.8,"48":12.8,"49":12.9,"50":12.9,"51":12.6,"52":12.5,"53":12.5,"63":8.5,"65":9.1,"66":8.8,"67":8.9,"68":8.9,"69":8.7,"70":8.5,"71":8.2,"72":12.4,"73":12.4,"74":12.5,"75":12.3,"76":12.3,"77":12.2,"78":12.1,"79":11.9,"80":11.3,"225":12.9,"226":13.0,"227":13.2,"228":13.3,"229":13.6,"230":13.7,"231":13.2,"232":12.8,"233":12.8,"81":15.2,"82":15.1,"83":15.2,"84":15.2,"85":15.1,"86":15.0,"87":14.9,"88":14.9,"89":14.9,"90":10.5,"91":10.8,"92":10.5,"93":10.2,"94":9.9,"95":9.5,"96":9.5,"97":9.3,"98":9.1,"144":11.1,"145":11.6,"146":11.1,"147":10.8,"148":10.9,"149":11.0,"150":10.9,"151":10.9,"152":10.6,"54":15.3,"62":13.4,"99":12.2,"100":12.2,"101":12.2,"102":8.3,"103":11.0,"104":10.9,"105":10.9,"106":10.7,"107":10.6,"126":8.3,"127":8.2,"128":8.2,"129":8.1,"130":8.3,"131":8.6,"132":10.8,"133":11.0,"134":11.0,"135":8.7,"136":9.4,"137":10.8,"138":10.0,"139":9.3,"140":9.3,"142":9.2,"143":9.3,"117":9.9,"118":9.8,"119":9.8,"120":9.9,"121":10.6,"122":10.7,"123":10.9,"124":11.2,"125":11.4,"153":10.0,"154":9.8,"155":9.8,"156":9.3,"157":9.0,"158":9.1,"159":8.9,"160":8.8,"161":8.7,"164":16.8,"165":16.9,"166":16.9,"167":16.7,"168":16.6,"169":16.5,"170":16.4,"180":10.8,"181":10.8,"182":10.5,"183":10.6,"184":10.2,"185":9.9,"186":9.8,"187":10.9,"188":10.9,"189":10.9,"190":11.3,"191":11.4,"192":8.2,"193":10.8,"194":10.5,"195":10.4,"196":10.1,"197":10.6,"198":15.5,"199":15.2,"200":14.8,"201":14.8,"202":14.8,"203":14.5,"204":14.5,"205":14.3,"206":14.1,"234":12.5,"235":12.9,"236":13.1,"237":13.1,"238":12.9,"239":13.0,"240":12.6,"241":12.7,"242":12.7,"207":12.6,"208":12.7,"209":12.7,"210":11.2,"211":11.2,"212":11.2,"213":11.4,"215":11.0,"216":14.0,"217":14.0,"218":13.7,"219":14.0,"220":14.1,"221":14.2,"222":14.2,"223":14.3,"224":14.3,"243":19.8,"244":17.2,"245":17.2,"246":24.1,"247":16.6,"248":18.3,"249":18.4},"status":{"1":"d","2":"d","3":"d","14":"b","43":"d","44":"d","45":"d","46":"d","47":"d","48":"d","49":"d","50":"d","51":"d","52":"d","53":"d","65":"d","66":"d","67":"d","81":"d","82":"d","83":"d","84":"d","85":"d","86":"d","87":"d","88":"d","89":"d","91":"d","92":"d","95":"d","96":"d","97":"d","144":"d","62":"d","103":"d","104":"d","105":"d","106":"d","107":"d","130":"d","138":"d","141":"d","142":"d","185":"b","191":"d","192":"d","194":"d","195":"d","196":"d","197":"d","212":"d","213":"d","214":"d","215":"d","245":"d","248":"d","249":"d"},"id":["freq","unit","isced11","geo","time"],"size":[1,1,1,28,9],"dimension":{"freq":{"label":"Time frequency","category":{"index":{"A":0},"label":{"A":"Annual"}}},"unit":{"label":"Unit of measure","category":{"index":{"RT":0},"label":{"RT":"Rate"}}},"isced11":{"label":"International Standard Classification of Education (ISCED 2011)","category":{"index":{"ED1-3":0},"label":{"ED1-3":"Primary and secondary education (levels 1-3)"}}},"geo":{"label":"Geopolitical entity (reporting)","category":{"index":{"BE":0,"BG":1,"CZ":2,"DK":3,"DE":4,"EE":5,"IE":6,"EL":7,"ES":8,"FR":9,"HR":10,"IT":11,"CY":12,"LV":13,"LT":14,"LU":15,"HU":16,"MT":17,"NL":18,"AT":19,"PL":20,"PT":21,"RO":22,"SI":23,"SK":24,"FI":25,"SE":26,"UK":27},"label":{"BE":"Belgium","BG":"Bulgaria","CZ":"Czechia","DK":"Denmark","DE":"Germany","EE":"Estonia","IE":"Ireland","EL":"Greece","ES":"Spain","FR":"France","HR":"Croatia","IT":"Italy","CY":"Cyprus","LV":"Latvia","LT":"Lithuania","LU":"Luxembourg","HU":"Hungary","MT":"Malta","NL":"Netherlands","AT":"Austria","PL":"Poland","PT":"Portugal","RO":"Romania","SI":"Slovenia","SK":"Slovakia","FI":"Finland","SE":"Sweden","UK":"United Kingdom"}}},"time":{"label":"Time","category":{"index":{"2013":0,"2014":1,"2015":2,"2016":3,"2017":4,"2018":5,"2019":6,"2020":7,"2021":8},"label":{"2013":"2013","2014":"2014","2015":"2015","2016":"2016","2017":"2017","2018":"2018","2019":"2019","2020":"2020","2021":"2021"}}}},"extension":{"lang":"EN","id":"EDUC_UOE_PERP04","agencyId":"ESTAT","version":"1.0","datastructure":{"id":"EDUC_UOE_PERP04","agencyId":"ESTAT","version":"29.1"},"annotation":[{"type":"DISSEMINATION_DOI_XML","title":"<adms:identifier xmlns:adms=\"http://www.w3.org/ns/adms#\" xmlns:skos=\"http://www.w3.org/2004/02/skos/core.html\" xmlns:dct=\"http://purl.org/dc/terms/\" xmlns:rdf=\"http://www.w3.org/1999/02/22-rdf-syntax-ns#\"><adms:Identifier rdf:about=\"https://doi.org/10.2908/EDUC_UOE_PERP04\"><skos:notation rdf:datatype=\"http://purl.org/spar/datacite/doi\">10.2908/EDUC_UOE_PERP04</skos:notation><dct:creator rdf:resource=\"http://publications.europa.eu/resource/authority/corporate-body/ESTAT\"/><dct:issued rdf:datatype=\"http://www.w3.org/2001/XMLSchema#date\">2023-01-19</dct:issued></adms:Identifier></adms:identifier>"},{"type":"DISSEMINATION_OBJECT_TYPE","title":"DATASET"},{"type":"ESMS_HTML","title":"Explanatory texts (metadata)","href":"https://ec.europa.eu/eurostat/cache/metadata/en/educ_uoe_enr_esms.htm"},{"type":"ESMS_SDMX","title":"Explanatory texts (metadata)","href":"https://ec.europa.eu/eurostat/api/dissemination/files?file=metadata/educ_uoe_enr_esms.sdmx.zip"},{"type":"OBS_COUNT","title":"4574"},{"type":"OBS_PERIOD_OVERALL_LATEST","title":"2021"},{"type":"OBS_PERIOD_OVERALL_OLDEST","title":"2013"},{"type":"SOURCE_INSTITUTIONS","text":"Eurostat"},{"type":"UPDATE_DATA","date":"2023-07-06T23:00:00+0200"},{"type":"UPDATE_STRUCTURE","date":"2023-05-26T23:00:00+0200"}],"status":{"label":{"b":"break in time series","d":"definition differs (see metadata)"}},"positions-with-no-data":{"freq":[],"unit":[],"isced11":[],"geo":[],"time":[]}}}